tests/README.md
tests/__init__.py
tests/run_test.py
tests/test_config.py
tests/problems/asp/birds_fly.md
tests/problems/asp/company_controls.md
tests/problems/asp/package_status_unsat.md
tests/problems/asp/party_invitation.md
tests/problems/asp/shift_assignment.md
tests/problems/asp/test.md
tests/problems/maxsat/equipment_purchase.md
tests/problems/maxsat/network_monitoring.md
tests/problems/maxsat/package_selection.md
tests/problems/maxsat/task_assignment.md
tests/problems/maxsat/test.md
tests/problems/maxsat/workshop_scheduling_unsat.md
tests/problems/mzn/carpet_cutting.md
tests/problems/mzn/test.md
tests/problems/mzn/tsp.md
tests/problems/mzn/university_scheduling.md
tests/problems/mzn/university_scheduling_unsat.md
tests/problems/mzn/zebra.md
tests/problems/pysat/equitable_coloring_hajos.md
tests/problems/pysat/furniture_arrangement.md
tests/problems/pysat/no_three_in_line_5x5.md
tests/problems/pysat/petersen_12_coloring_unsat.md
tests/problems/pysat/sudoku_16x16.md
tests/problems/pysat/test.md
tests/problems/z3/array_property_verifier.md
tests/problems/z3/bounded_sum_unsat.md
tests/problems/z3/cryptarithmetic.md
tests/problems/z3/processor_verification.md
tests/problems/z3/sos_induction.md
tests/problems/z3/test.md
mcp_solver/solution.py
mcp_solver/asp/__init__.py
mcp_solver/asp/environment.py
mcp_solver/asp/error_handling.py
mcp_solver/asp/model_manager.py
mcp_solver/asp/solution.py
mcp_solver/asp/test_setup.py
mcp_solver/asp/templates/__init__.py
mcp_solver/asp/templates/basic_templates.py
mcp_solver/client/__init__.py
mcp_solver/client/client.py
mcp_solver/client/llm_factory.py
mcp_solver/client/mcp_tool_adapter.py
mcp_solver/client/test_setup.py
mcp_solver/client/token_callback.py
mcp_solver/client/token_counter.py
mcp_solver/client/tool_capability_detector.py
mcp_solver/client/tool_stats.py
mcp_solver/core/__init__.py
mcp_solver/core/__main__.py
mcp_solver/core/base_manager.py
mcp_solver/core/base_model_manager.py
mcp_solver/core/constants.py
iflow_mcp_mcp_solver-3.4.1.dist-info/METADATA
iflow_mcp_mcp_solver-3.4.1.dist-info/WHEEL
iflow_mcp_mcp_solver-3.4.1.dist-info/entry_points.txt
iflow_mcp_mcp_solver-3.4.1.dist-info/licenses/LICENSE
iflow_mcp_mcp_solver-3.4.1.dist-info/RECORD
